Metadata-Version: 2.1
Name: odoo-addon-mrp_production_serial_matrix
Version: 17.0.1.2.0
Requires-Python: >=3.10
Requires-Dist: odoo-addon-web_widget_x2many_2d_matrix>=17.0dev,<17.1dev
Requires-Dist: odoo>=17.0a,<17.1dev
Summary: MRP Production Serial Matrix
Home-page: https://github.com/OCA/manufacture
License: AGPL-3
Author: ForgeFlow, Odoo Community Association (OCA)
Author-email: support@odoo-community.org
Classifier: Programming Language :: Python
Classifier: Framework :: Odoo
Classifier: Framework :: Odoo :: 17.0
Classifier: License :: OSI Approved :: GNU Affero General Public License v3
